{
  "key": "group_initiatives_section",
  "title": "Ініціативи (Слайдер)",
  "fields": [
    {
      "key": "field_show_initiatives_section",
      "label": "Показувати секцію",
      "name": "show_initiatives_section",
      "aria-label": "",
      "type": "true_false",
      "instructions": "",
      "required": false,
      "conditional_logic": false,
      "wrapper": {
        "width": "",
        "class": "",
        "id": ""
      },
      "ui": 1,
      "default_value": 0,
      "message": "",
      "ui_on_text": "",
      "ui_off_text": ""
    },
    {
      "key": "field_initiatives_section_title",
      "label": "Заголовок секції",
      "name": "initiatives_section_title",
      "aria-label": "",
      "type": "text",
      "instructions": "",
      "required": 0,
      "conditional_logic": false,
      "wrapper": {
        "width": "",
        "class": "",
        "id": ""
      },
      "default_value": "ВІРИМО В ОСВІТУ, ЩО РУХАЄ ВПЕРЕД",
      "maxlength": "",
      "placeholder": "",
      "prepend": "",
      "append": ""
    },
    {
      "key": "field_initiatives_section_subtitle",
      "label": "Підзаголовок",
      "name": "initiatives_section_subtitle",
      "aria-label": "",
      "type": "textarea",
      "instructions": "",
      "required": false,
      "conditional_logic": false,
      "wrapper": {
        "width": "",
        "class": "",
        "id": ""
      },
      "rows": 3,
      "default_value": "ТОМУ ПІДТРИМУЄМО СОЦІАЛЬНІ ТА ОСВІТНІ ІНІЦІАТИВИ Й ЗАПУСКАЄМО ВЛАСНІ",
      "new_lines": "",
      "maxlength": "",
      "placeholder": ""
    },
    {
      "key": "field_initiatives_list",
      "label": "Слайди ініціатив",
      "name": "initiatives_list",
      "aria-label": "",
      "type": "repeater",
      "instructions": "",
      "required": false,
      "conditional_logic": false,
      "wrapper": {
        "width": "",
        "class": "",
        "id": ""
      },
      "layout": "block",
      "button_label": "+ Додати ініціативу",
      "min": 0,
      "max": 0,
      "rows_per_page": 20,
      "collapsed": "",
      "sub_fields": [
        {
          "key": "field_6939a266ad31e",
          "label": "Посилання на ресурс",
          "name": "link",
          "aria-label": "",
          "type": "url",
          "instructions": "",
          "required": 0,
          "conditional_logic": 0,
          "wrapper": {
            "width": "",
            "class": "",
            "id": ""
          },
          "default_value": "",
          "placeholder": "",
          "parent_repeater": "field_initiatives_list"
        },
        {
          "key": "field_initiative_photo",
          "label": "Фото",
          "name": "photo",
          "aria-label": "",
          "type": "image",
          "instructions": "",
          "required": 0,
          "conditional_logic": 0,
          "wrapper": {
            "width": "",
            "class": "",
            "id": ""
          },
          "return_format": "array",
          "library": "all",
          "min_width": "",
          "min_height": "",
          "min_size": "",
          "max_width": "",
          "max_height": "",
          "max_size": "",
          "mime_types": "",
          "preview_size": "medium",
          "parent_repeater": "field_initiatives_list"
        },
        {
          "key": "field_initiative_description",
          "label": "Опис",
          "name": "description",
          "aria-label": "",
          "type": "textarea",
          "instructions": "",
          "required": false,
          "conditional_logic": false,
          "wrapper": {
            "width": "",
            "class": "",
            "id": ""
          },
          "rows": 3,
          "default_value": "",
          "new_lines": "",
          "maxlength": "",
          "placeholder": "",
          "parent_repeater": "field_initiatives_list"
        }
      ]
    }
  ],
  "location": [
    [
      {
        "param": "page_template",
        "operator": "==",
        "value": "page-templates/homepage.php"
      }
    ]
  ],
  "menu_order": 0,
  "position": "normal",
  "style": "default",
  "label_placement": "top",
  "instruction_placement": "label",
  "hide_on_screen": "",
  "active": true,
  "description": "Секція ініціатив з можливістю створення слайдів",
  "show_in_rest": 0,
  "modified": 1765386648
}
